odoo/addons/user_all_groups/README.rst
odoo/addons/user_all_groups/__init__.py
odoo/addons/user_all_groups/__manifest__.py
odoo/addons/user_all_groups/demo/res_users.xml
odoo/addons/user_all_groups/i18n/es.po
odoo/addons/user_all_groups/i18n/fr.po
odoo/addons/user_all_groups/i18n/it.po
odoo/addons/user_all_groups/i18n/user_all_groups.pot
odoo/addons/user_all_groups/models/__init__.py
odoo/addons/user_all_groups/models/res_groups.py
odoo/addons/user_all_groups/models/res_users.py
odoo/addons/user_all_groups/readme/CONTRIBUTORS.rst
odoo/addons/user_all_groups/readme/DESCRIPTION.rst
odoo/addons/user_all_groups/readme/INSTALL.rst
odoo/addons/user_all_groups/static/description/icon.png
odoo/addons/user_all_groups/static/description/index.html
odoo/addons/user_all_groups/static/description/view_res_users_form.png
odoo/addons/user_all_groups/tests/__init__.py
odoo/addons/user_all_groups/tests/test_module.py
odoo/addons/user_all_groups/views/view_res_users.xml
odoo_addon_user_all_groups-16.0.1.0.1.8.dist-info/METADATA
odoo_addon_user_all_groups-16.0.1.0.1.8.dist-info/WHEEL
odoo_addon_user_all_groups-16.0.1.0.1.8.dist-info/top_level.txt
odoo_addon_user_all_groups-16.0.1.0.1.8.dist-info/RECORD
