Metadata-Version: 2.1
Name: odoo-addon-user-all-groups
Version: 16.0.1.0.1.8
Summary: Automatically add admin user to all the groups
Home-page: https://github.com/OCA/server-ux
Author: GRAP, Odoo Community Association (OCA)
Author-email: support@odoo-community.org
License: AGPL-3
Platform: UNKNOWN
Classifier: Programming Language :: Python
Classifier: Framework :: Odoo
Classifier: Framework :: Odoo :: 16.0
Classifier: License :: OSI Approved :: GNU Affero General Public License v3
Requires-Python: >=3.10
Requires-Dist: odoo <16.1dev,>=16.0a
